[
    {
        "name": "bookmebus",
        "logo": "bookmebus.png",
        "url": ""
    },{
        "name": "codingate",
        "logo": "codingate.png",
        "url": ""
    },{
        "name": "toursanak",
        "logo": "toursanak.png",
        "url": ""
    },{
        "name": "seavphojivit",
        "logo": "seavphojivit.png",
        "url": ""
    },{
        "name": "fado",
        "logo": "fado.png",
        "url": ""
    },{
        "name": "koompi",
        "logo": "koompi.png",
        "url": "https://www.koompi.com"
    },{
        "name": "vitaminair",
        "logo": "vitaminair.png",
        "url": "https://www.vitaminair.org"
    },{
        "name": "grood",
        "logo": "grood.png",
        "url": "https://www.getgrood.com"
    },{
        "name": "selendra",
        "logo": "selendra.png",
        "url": "https://www.selendra.com"
    },{
        "name": "hospicare",
        "logo": "hospicare.png",
        "url": ""
    }
]
